yamlizer/__init__.py
yamlizer/yamlizable.py
yamlizer/yamlizer.py
yamlizer/yamlmapper.py
yamlizer-1.0.0.dist-info/LICENSE.rst
yamlizer-1.0.0.dist-info/WHEEL
yamlizer-1.0.0.dist-info/METADATA
yamlizer-1.0.0.dist-info/RECORD
